redondear/__init__.py
redondear/redondear.py
redondear_dsalinas-0.0.3.dist-info/LICENCE
redondear_dsalinas-0.0.3.dist-info/LICENSE
redondear_dsalinas-0.0.3.dist-info/METADATA
redondear_dsalinas-0.0.3.dist-info/WHEEL
redondear_dsalinas-0.0.3.dist-info/top_level.txt
redondear_dsalinas-0.0.3.dist-info/RECORD
